gstreamer_plugins_restricted-1.27.90.data/purelib/gstreamer_plugins_restricted/__init__.py
gstreamer_plugins_restricted-1.27.90.data/purelib/gstreamer_plugins_restricted/bin/rtmp-1.dll
gstreamer_plugins_restricted-1.27.90.data/purelib/gstreamer_plugins_restricted/bin/vo-aacenc-0.dll
gstreamer_plugins_restricted-1.27.90.data/purelib/gstreamer_plugins_restricted/bin/vvdec.dll
gstreamer_plugins_restricted-1.27.90.data/purelib/gstreamer_plugins_restricted/lib/gstreamer-1.0/gstasf.dll
gstreamer_plugins_restricted-1.27.90.data/purelib/gstreamer_plugins_restricted/lib/gstreamer-1.0/gstasfmux.dll
gstreamer_plugins_restricted-1.27.90.data/purelib/gstreamer_plugins_restricted/lib/gstreamer-1.0/gstdvdlpcmdec.dll
gstreamer_plugins_restricted-1.27.90.data/purelib/gstreamer_plugins_restricted/lib/gstreamer-1.0/gstdvdsub.dll
gstreamer_plugins_restricted-1.27.90.data/purelib/gstreamer_plugins_restricted/lib/gstreamer-1.0/gstmpegpsdemux.dll
gstreamer_plugins_restricted-1.27.90.data/purelib/gstreamer_plugins_restricted/lib/gstreamer-1.0/gstmpegpsmux.dll
gstreamer_plugins_restricted-1.27.90.data/purelib/gstreamer_plugins_restricted/lib/gstreamer-1.0/gstmpegtsdemux.dll
gstreamer_plugins_restricted-1.27.90.data/purelib/gstreamer_plugins_restricted/lib/gstreamer-1.0/gstmpegtsmux.dll
gstreamer_plugins_restricted-1.27.90.data/purelib/gstreamer_plugins_restricted/lib/gstreamer-1.0/gstrealmedia.dll
gstreamer_plugins_restricted-1.27.90.data/purelib/gstreamer_plugins_restricted/lib/gstreamer-1.0/gstrtmp.dll
gstreamer_plugins_restricted-1.27.90.data/purelib/gstreamer_plugins_restricted/lib/gstreamer-1.0/gstvoaacenc.dll
gstreamer_plugins_restricted-1.27.90.data/purelib/gstreamer_plugins_restricted/lib/gstreamer-1.0/gstvvdec.dll
gstreamer_plugins_restricted-1.27.90.dist-info/METADATA
gstreamer_plugins_restricted-1.27.90.dist-info/WHEEL
gstreamer_plugins_restricted-1.27.90.dist-info/top_level.txt
gstreamer_plugins_restricted-1.27.90.dist-info/RECORD
